devdeck_hue/__init__.py
devdeck_hue/brightness.py
devdeck_hue/toggle.py
devdeck_hue/assets/brightness-high.png
devdeck_hue/assets/brightness-low.png
devdeck_hue/assets/lightbulb-filled.png
devdeck_hue/assets/lightbulb-outlined.png
tests/__init__.py
tests/testing_utils.py
tests/devdeck_hue/__init__.py
tests/devdeck_hue/conftest.py
tests/devdeck_hue/test_brightness.py
tests/devdeck_hue/test_keylight_toggle_control.py
devdeck_hue-0.0.1.dist-info/METADATA
devdeck_hue-0.0.1.dist-info/WHEEL
devdeck_hue-0.0.1.dist-info/top_level.txt
devdeck_hue-0.0.1.dist-info/RECORD
