Metadata-Version: 2.1
Name: devdeck-hue
Version: 0.0.1
Summary: Philips Hue controls for DevDeck.
Home-page: https://github.com/nicdumz/devdeck-hue
Author: Nicolas Dumazet
License: MIT
Platform: UNKNOWN
Requires-Dist: assertpy (==1.1)
Requires-Dist: devdeck-core (==1.0.7)
Requires-Dist: phue (==1.1)
Requires-Dist: pytest (==6.2.1)
Requires-Dist: vcrpy (==4.1.1)
